LICENSE
README.md
setup.py
stats_utils/Binomialdistribution.py
stats_utils/Gaussiandistribution.py
stats_utils/Generaldistribution.py
stats_utils/__init__.py
stats_utils.egg-info/PKG-INFO
stats_utils.egg-info/SOURCES.txt
stats_utils.egg-info/dependency_links.txt
stats_utils.egg-info/not-zip-safe
stats_utils.egg-info/top_level.txt
tests/test.py