Metadata-Version: 2.1
Name: stats-utils
Version: 0.1.1
Summary: Probability and Statistics Utilities library. Currently only Distributions
Author: Kawalpreet Deol
Author-email: 
License-File: LICENSE
